{
    "My Behavior": {
        "checkpoints": [
            {
                "steps": 7780,
                "file_path": "results\\2210251830\\My Behavior\\My Behavior-7780.onnx",
                "reward": 0.0,
                "creation_time": 1666715502.1865213,
                "auxillary_file_paths": [
                    "results\\2210251830\\My Behavior\\My Behavior-7780.pt"
                ]
            }
        ],
        "final_checkpoint": {
            "steps": 7780,
            "file_path": "results\\2210251830\\My Behavior.onnx",
            "reward": 0.0,
            "creation_time": 1666715502.1865213,
            "auxillary_file_paths": [
                "results\\2210251830\\My Behavior\\My Behavior-7780.pt"
            ]
        }
    },
    "metadata": {
        "stats_format_version": "0.3.0",
        "mlagents_version": "0.28.0",
        "torch_version": "1.7.1+cu110"
    }
}